tsctools/__init__.py
tsctools/xarray2hdf5.py
tsctools-0.0.4.dist-info/METADATA
tsctools-0.0.4.dist-info/WHEEL
tsctools-0.0.4.dist-info/licenses/LICENSE
tsctools-0.0.4.dist-info/RECORD
